{
  "An Giang": [ "Châu Đốc", "Châu Phú", "Tân Châu" ],
  "Bà Rịa - Vũng Tàu": [ "Châu Đức", "Đất Đỏ" ],
  "Bắc Giang": [ "Hiệp Hòa", "Lạng Giang", "Sơn Động" ],
  "Bắc Kạn": [ "Ba Bể", "Ngân Sơn", "Chợ Đồn" ],
  "Bạc Liêu": [ "Hồng Dân", "Giá Rai", "Vĩnh Lợi" ],
  "Bắc Ninh": [ "Tiên Du", "Từ Sơn", "Yên Phong" ],
  "Bến Tre": [ "Ba Tri", "Châu Thành", "Mỏ Cày Nam" ],
  "Bình Định": [ "Quy Nhơn", "Hoài Nhơn", "Tuy Phước", "An Nhơn" ],
  "Bình Dương": [ "Thủ Dầu Một", "Bến Cát", "Dĩ An", "Tân Uyên" ],
  "Bình Phước": [ "Đồng Xoài", "Phước Long", "Bù Đăng", "Chơn Thành" ],
  "Bình Thuận": [ "Phan Thiết", "La Gi", "Tuy Phong", "Bắc Bình" ],
  "Cà Mau": [ "Năm Căn", "Cái Nước", "Ngọc Hiển" ],
  "Cần Thơ": [ "Ninh Kiều", "Bình Thủy", "Cái Răng", "Thốt Nốt" ],
  "Cao Bằng": [ "Cao Bằng", "Trùng Khánh", "Hà Quảng", "Nguyên Bình" ],
  "Đà Nẵng": [ "Hải Châu", "Thanh Khê", "Liên Chiểu", "Sơn Trà" ],
  "Đắk Lắk": [ "Buôn Ma Thuột", "Ea H'leo", "Krông Pắc", "Cư M'gar" ],
  "Đắk Nông": [ "Gia Nghĩa", "Đắk Mil", "Cư Jút", "Krông Nô" ],
  "Điện Biên": [ "Điện Biên Phủ", "Mường Ảng", "Tủa Chùa", "Mường Chà" ],
  "Đồng Nai": [ "Biên Hòa", "Long Khánh", "Long Thành", "Trảng Bom" ],
  "Đồng Tháp": [ "Cao Lãnh", "Sa Đéc", "Lấp Vò", "Châu Thành" ],
  "Gia Lai": [ "Pleiku", "An Khê", "Ayun Pa", "Chư Sê" ],
  "Hà Giang": [ "Hà Giang", "Quản Bạ", "Yên Minh", "Đồng Văn" ],
  "Hà Nam": [ "Phủ Lý", "Duy Tiên", "Kim Bảng", "Thanh Liêm" ],
  "Hà Nội": [ "Ba Đình", "Hoàn Kiếm", "Tây Hồ", "Long Biên" ],
  "Hà Tĩnh": [ "Hồng Lĩnh", "Kỳ Anh", "Cẩm Xuyên" ],
  "Hải Dương": [ "Hải Dương", "Chí Linh", "Kinh Môn", "Ninh Giang" ],
  "Hải Phòng": [ "Hồng Bàng", "Lê Chân", "Ngô Quyền", "Thủy Nguyên" ],
  "Hậu Giang": [ "Vị Thanh", "Ngã Bảy", "Châu Thành", "Phụng Hiệp" ],
  "Hòa Bình": [ "Lạc Sơn", "Mai Châu", "Cao Phong" ],
  "Hưng Yên": [ "Mỹ Hào", "Khoái Châu", "Văn Lâm" ],
  "Khánh Hòa": [ "Nha Trang", "Cam Ranh", "Diên Khánh", "Vạn Ninh" ],
  "Kiên Giang": [ "Rạch Giá", "Phú Quốc", "Hà Tiên", "Giồng Riềng" ],
  "Kon Tum": [ "Đắk Hà", "Ngọc Hồi", "Đắk Tô" ],
  "Lai Châu": [ "Lai Châu", "Phong Thổ", "Tam Đường", "Tân Uyên" ],
  "Lâm Đồng": [ "Đà Lạt", "Bảo Lộc", "Đức Trọng", "Di Linh" ],
  "Lạng Sơn": [ "Cao Lộc", "Chi Lăng", "Bình Gia" ],
  "Lào Cai": [ "Lào Cai", "Sa Pa", "Bát Xát", "Bảo Thắng" ],
  "Long An": [ "Tân An", "Bến Lức", "Đức Hòa", "Cần Giuộc" ],
  "Nam Định": [ "Giao Thủy", "Hải Hậu", "Ý Yên" ],
  "Nghệ An": [ "Vinh", "Cửa Lò", "Quỳnh Lưu", "Con Cuông" ],
  "Ninh Bình": [ "Ninh Bình", "Tam Điệp", "Gia Viễn", "Hoa Lư" ],
  "Ninh Thuận": [ "Phan Rang - Tháp Chàm", "Ninh Hải", "Ninh Phước", "Thuận Bắc" ],
  "Phú Thọ": [ "Việt Trì", "Phú Thọ", "Thanh Sơn", "Đoan Hùng" ],
  "Phú Yên": [ "Tuy Hòa", "Sông Cầu", "Đồng Xuân", "Tuy An" ],
  "Quảng Bình": [ "Đồng Hới", "Ba Đồn", "Bố Trạch", "Quảng Trạch" ],
  "Quảng Nam": [ "Tam Kỳ", "Hội An", "Điện Bàn", "Đại Lộc" ],
  "Quảng Ngãi": [ "Đức Phổ", "Bình Sơn", "Sơn Tịnh" ],
  "Quảng Ninh": [ "Hạ Long", "Cẩm Phả", "Móng Cái", "Uông Bí" ],
  "Quảng Trị": [ "Đông Hà", "Quảng Trị", "Cam Lộ", "Gio Linh" ],
  "Sóc Trăng": [ "Sóc Trăng", "Vĩnh Châu", "Kế Sách", "Mỹ Xuyên" ],
  "Sơn La": [ "Mộc Châu", "Mai Sơn", "Sông Mã" ],
  "Tây Ninh": [ "Tây Ninh", "Hòa Thành", "Trảng Bàng", "Tân Châu" ],
  "Thái Bình": [ "Quỳnh Phụ", "Tiền Hải", "Kiến Xương" ],
  "Thái Nguyên": [ "Thái Nguyên", "Sông Công", "Đại Từ", "Phổ Yên" ],
  "Thanh Hóa": [ "Sầm Sơn", "Bỉm Sơn", "Nghi Sơn" ],
  "Thừa Thiên Huế": [ "Huế", "Hương Thủy", "Hương Trà", "Phong Điền" ],
  "Tiền Giang": [ "Mỹ Tho", "Gò Công", "Cai Lậy", "Châu Thành" ],
  "TP. Hồ Chí Minh": [ "Quận 1", "Quận 2", "Quận 3", "Quận 4" ],
  "Trà Vinh": [ "Trà Vinh", "Càng Long", "Cầu Kè", "Tiểu Cần" ],
  "Tuyên Quang": [ "Yên Sơn", "Chiêm Hóa", "Sơn Dương" ],
  "Vĩnh Long": [ "Vĩnh Long", "Bình Minh", "Long Hồ", "Tam Bình" ],
  "Vĩnh Phúc": [ "Vĩnh Yên", "Phúc Yên", "Tam Đảo", "Yên Lạc" ],
  "Yên Bái": [ "Nghĩa Lộ", "Văn Chấn", "Mù Cang Chải" ]
}